{
	"name": "trigger_once_off_load_from_oac",
	"properties": {
		"annotations": [],
		"runtimeState": "Stopped",
		"pipelines": [
			{
				"pipelineReference": {
					"referenceName": "pipe_BICS_MRTG_90MV",
					"type": "PipelineReference"
				}
			},
			{
				"pipelineReference": {
					"referenceName": "pipe_BIA_GL_PERIODS_R11V",
					"type": "PipelineReference"
				}
			},
			{
				"pipelineReference": {
					"referenceName": "pipe_oac_to_aoac_BIA_GL_LINES_R11V",
					"type": "PipelineReference"
				}
			},
			{
				"pipelineReference": {
					"referenceName": "pipe_oac_to_aoac_CMP3_dolar_101769",
					"type": "PipelineReference"
				}
			},
			{
				"pipelineReference": {
					"referenceName": "pipe_oac_to_aoac_BIA_GL_BATCHES_R11V",
					"type": "PipelineReference"
				}
			},
			{
				"pipelineReference": {
					"referenceName": "pipe_oac_to_aoac_BICS_REVENUE_FT2",
					"type": "PipelineReference"
				}
			},
			{
				"pipelineReference": {
					"referenceName": "pipe_BICS_MRTG_SITE_USAGE",
					"type": "PipelineReference"
				}
			},
			{
				"pipelineReference": {
					"referenceName": "pipe_oac_to_aoac_BIA_POWER_CONTRACT_LINES",
					"type": "PipelineReference"
				}
			},
			{
				"pipelineReference": {
					"referenceName": "pipe_oac_to_aoac_BIA_GL_JOURNALS_R11V",
					"type": "PipelineReference"
				}
			},
			{
				"pipelineReference": {
					"referenceName": "pipe_oac_to_aoac_BIA_GL_HEADERS_R11V",
					"type": "PipelineReference"
				}
			},
			{
				"pipelineReference": {
					"referenceName": "pipe_oac_to_aoac_BIA_ENCL_TAKW",
					"type": "PipelineReference"
				}
			},
			{
				"pipelineReference": {
					"referenceName": "pipe_oac_to_aoac_BIA_ENCL_TKWH",
					"type": "PipelineReference"
				}
			},
			{
				"pipelineReference": {
					"referenceName": "pipe_oac_to_aoac_BIA_ENCL_TSQFT",
					"type": "PipelineReference"
				}
			},
			{
				"pipelineReference": {
					"referenceName": "pipe_BICS_PO_AP_WORKFLOW",
					"type": "PipelineReference"
				}
			},
			{
				"pipelineReference": {
					"referenceName": "pipe_oac_to_aoac_BIA_POWER_KW_CAGE_MON_V",
					"type": "PipelineReference"
				}
			},
			{
				"pipelineReference": {
					"referenceName": "pipe_oac_to_aoac_BICS_IPROCUREMENT_LICENSE_V",
					"type": "PipelineReference"
				}
			}
		],
		"type": "ScheduleTrigger",
		"typeProperties": {
			"recurrence": {
				"frequency": "Day",
				"interval": 1,
				"startTime": "2020-01-01T09:40:00Z",
				"endTime": "2020-01-01T09:40:00Z",
				"timeZone": "UTC"
			}
		}
	}
}